manb/__init__.py
manb/arch.py
manb/comp.py
manb/env.py
manb/ex.py
manb/export.py
manb/gfile.py
manb/item.py
manb/log.py
manb/msc.py
manb/pr.py
manb/puml.py
manb/ra.py
manb/req.py
manb/sd.py
manb/va.py
manb-0.0.45.dist-info/LICENSE
manb-0.0.45.dist-info/METADATA
manb-0.0.45.dist-info/WHEEL
manb-0.0.45.dist-info/top_level.txt
manb-0.0.45.dist-info/RECORD
