Metadata-Version: 2.1
Name: manb
Version: 0.0.45
Summary: Mission Aware Notebook
Home-page: https://github.com/tsherburne/de-textbook
Author: Virginia Tech
Author-email: info@mission-aware.net
License: UNKNOWN
Project-URL: Bug Tracker, https://github.com/tsherburne/de-textbook/issues
Platform: UNKNOWN
Classifier: Programming Language :: Python :: 3
Classifier: License :: OSI Approved :: MIT License
Classifier: Operating System :: OS Independent
Requires-Python: >=3.6
License-File: LICENSE
Requires-Dist: itables
Requires-Dist: requests
Requires-Dist: ipywidgets
Requires-Dist: pandas
